funlab/auth/__init__.py
funlab/auth/conf/plugin.toml
funlab/auth/forms.py
funlab/auth/templates/logo.html
funlab/auth/templates/logout.html
funlab/auth/templates/register.html
funlab/auth/templates/resetpass.html
funlab/auth/templates/settings.html
funlab/auth/templates/sign-in-cover.html
funlab/auth/templates/sign-in-illustration.html
funlab/auth/templates/sign-in.html
funlab/auth/user.py
funlab/auth/view.py
funlab_auth-0.2.6.dist-info/entry_points.txt
funlab_auth-0.2.6.dist-info/LICENSE
funlab_auth-0.2.6.dist-info/METADATA
funlab_auth-0.2.6.dist-info/WHEEL
funlab_auth-0.2.6.dist-info/RECORD
